{
	"category":"T03",
	"dataDefinition":null,
	"dataType":"float",
	"defaultValue":null,
	"deprecated":false,
	"description":"vertical distance between a specified earth surface to an underground surface below which the ground is wholly saturated with water under normal atmospheric pressure.\nAs the reference for the earth surface it is recommended to apply the true altitude above mean sea level.",
	"elementType":["ATTRIBUTE","MEASUREPOINT"],
	"identifier":"groundwater_level",
	"name":{
		"defaultValue":"groundwater level",
		"i18nValue":{
			"en_US":"groundwater level",
			"zh_CN":null
		}
	},
	"unit":"m",
	"version":"1.0"
}