{
	"category":"T03",
	"dataDefinition":null,
	"dataType":"double",
	"defaultValue":null,
	"deprecated":false,
	"description":"value as specified by level (miNomax) of the length of the x-coordinate of the location of a point on the symmetry-axis of a constructive solid geometry primitive.",
	"elementType":["ATTRIBUTE","MEASUREPOINT"],
	"identifier":"x-coordinate_position_location",
	"name":{
		"defaultValue":"x-coordinate position location",
		"i18nValue":{
			"en_US":"x-coordinate position location",
			"zh_CN":null
		}
	},
	"unit":"m",
	"version":"1.0"
}