{
	"category":"Q56",
	"dataDefinition":null,
	"dataType":"int",
	"defaultValue":null,
	"deprecated":false,
	"description":"number of pitches between the terminals of an electric/electronic or electromechanical component parallel to the x-coordinate.",
	"elementType":["ATTRIBUTE","MEASUREPOINT"],
	"identifier":"number_of_pitches_x-axis",
	"name":{
		"defaultValue":"number of pitches (x-axis)",
		"i18nValue":{
			"en_US":"number of pitches (x-axis)",
			"zh_CN":"节距数（x 轴）"
		}
	},
	"unit":null,
	"version":"1.0"
}